repl_toolkit/__init__.py
repl_toolkit/async_repl.py
repl_toolkit/formatting.py
repl_toolkit/headless_repl.py
repl_toolkit/images.py
repl_toolkit/ptypes.py
repl_toolkit/actions/__init__.py
repl_toolkit/actions/action.py
repl_toolkit/actions/registry.py
repl_toolkit/completion/__init__.py
repl_toolkit/completion/prefix.py
repl_toolkit/completion/shell_expansion.py
repl_toolkit/tests/__init__.py
repl_toolkit/tests/conftest.py
repl_toolkit/tests/test_actions.py
repl_toolkit/tests/test_async_repl.py
repl_toolkit/tests/test_completion.py
repl_toolkit/tests/test_ctrl_c_cancel.py
repl_toolkit/tests/test_formatting.py
repl_toolkit/tests/test_headless.py
repl_toolkit/tests/test_image_utils.py
repl_toolkit/tests/test_images.py
repl_toolkit/tests/test_types.py
repl_toolkit-1.3.0.dist-info/licenses/LICENSE
repl_toolkit-1.3.0.dist-info/METADATA
repl_toolkit-1.3.0.dist-info/WHEEL
repl_toolkit-1.3.0.dist-info/top_level.txt
repl_toolkit-1.3.0.dist-info/RECORD
