Metadata-Version: 2.4
Name: repl-toolkit
Version: 1.3.0
Summary: A Python toolkit for building interactive REPL and headless interfaces with action support
Author-email: REPL Toolkit Contributors <martin.j.bartlett@gmail.com>
License: MIT
Project-URL: Homepage, https://github.com/bassmanitram/repl-toolkit
Project-URL: Documentation, https://repl-toolkit.readthedocs.io/
Project-URL: Repository, https://github.com/bassmanitram/repl-toolkit.git
Project-URL: Bug Tracker, https://github.com/bassmanitram/repl-toolkit/issues
Keywords: repl,cli,interactive,chat,toolkit,actions,keyboard,shortcuts
Classifier: Development Status :: 5 - Production/Stable
Classifier: Intended Audience :: Developers
Classifier: License :: OSI Approved :: MIT License
Classifier: Operating System :: OS Independent
Classifier: Programming Language :: Python :: 3
Classifier: Programming Language :: Python :: 3.8
Classifier: Programming Language :: Python :: 3.9
Classifier: Programming Language :: Python :: 3.10
Classifier: Programming Language :: Python :: 3.11
Classifier: Programming Language :: Python :: 3.12
Classifier: Topic :: Software Development :: Libraries :: Python Modules
Classifier: Topic :: Software Development :: User Interfaces
Classifier: Topic :: System :: Shells
Requires-Python: >=3.8
License-File: LICENSE
Requires-Dist: prompt-toolkit>=3.0.0
Requires-Dist: pyclip>=0.7.0
Provides-Extra: test
Requires-Dist: pytest>=6.0; extra == "test"
Requires-Dist: pytest-asyncio>=0.18.0; extra == "test"
Requires-Dist: pytest-cov>=3.0.0; extra == "test"
Provides-Extra: dev
Requires-Dist: black>=22.0.0; extra == "dev"
Requires-Dist: isort>=5.0.0; extra == "dev"
Requires-Dist: flake8>=4.0.0; extra == "dev"
Requires-Dist: mypy>=0.991; extra == "dev"
Requires-Dist: build>=0.8.0; extra == "dev"
Requires-Dist: twine>=4.0.0; extra == "dev"
Requires-Dist: pre-commit>=3.0.0; extra == "dev"
Requires-Dist: bandit>=1.7.0; extra == "dev"
Requires-Dist: safety>=2.0.0; extra == "dev"
Dynamic: license-file
